README.txt
setup.py
Products/__init__.py
Products.ATMemberSelectWidgetNG.egg-info/PKG-INFO
Products.ATMemberSelectWidgetNG.egg-info/SOURCES.txt
Products.ATMemberSelectWidgetNG.egg-info/dependency_links.txt
Products.ATMemberSelectWidgetNG.egg-info/entry_points.txt
Products.ATMemberSelectWidgetNG.egg-info/namespace_packages.txt
Products.ATMemberSelectWidgetNG.egg-info/not-zip-safe
Products.ATMemberSelectWidgetNG.egg-info/requires.txt
Products.ATMemberSelectWidgetNG.egg-info/top_level.txt
Products/ATMemberSelectWidget/ATMemberSelectDemo.py
Products/ATMemberSelectWidget/ATMemberSelectWidget.py
Products/ATMemberSelectWidget/HISTORY.txt
Products/ATMemberSelectWidget/README.txt
Products/ATMemberSelectWidget/__init__.py
Products/ATMemberSelectWidget/config.py
Products/ATMemberSelectWidget/version.txt
Products/ATMemberSelectWidget/Extensions/Install.py
Products/ATMemberSelectWidget/i18n/atmemberselectwidget-cs.po
Products/ATMemberSelectWidget/i18n/atmemberselectwidget-de.po
Products/ATMemberSelectWidget/i18n/atmemberselectwidget-en.po
Products/ATMemberSelectWidget/i18n/atmemberselectwidget-fi.po
Products/ATMemberSelectWidget/i18n/atmemberselectwidget-fr.po
Products/ATMemberSelectWidget/i18n/atmemberselectwidget-ja.po
Products/ATMemberSelectWidget/i18n/atmemberselectwidget-zh.po
Products/ATMemberSelectWidget/i18n/atmemberselectwidget.pot
Products/ATMemberSelectWidget/skins/atmemberselectwidget/memberselect.js
Products/ATMemberSelectWidget/skins/atmemberselectwidget/memberselect.js.metadata
Products/ATMemberSelectWidget/skins/atmemberselectwidget/memberselect.pt
Products/ATMemberSelectWidget/skins/atmemberselectwidget/memberselect_popup.pt
Products/ATMemberSelectWidget/skins/atmemberselectwidget/test_memberselect.pt
docs/HISTORY.txt