Metadata-Version: 1.0
Name: Products.ATMemberSelectWidgetNG
Version: 0.3.2
Summary: An archetypes widget similar to ATReferenceBrowserWidget which allows you to select a member's id or email from a popup search window. It can even be used without archetypes being installed in the site.
Home-page: http://plone.org/products/atmsw/
Author: Junyong Pan
Author-email: panjy@zopen.cn
License: GPL
Platform: UNKNOWN
Classifier: Programming Language :: Python
Classifier: Topic :: Software Development :: Libraries :: Python Modules
